nsdf_dark_matter_cli/__init__.py
nsdf_dark_matter_cli/cli.py
nsdf_dark_matter_cli/download.py
nsdf_dark_matter_cli/r_dataset.csv
tests/__init__.py
tests/test_cli.py
nsdf_dark_matter_cli-0.4.0.dist-info/METADATA
nsdf_dark_matter_cli-0.4.0.dist-info/WHEEL
nsdf_dark_matter_cli-0.4.0.dist-info/entry_points.txt
nsdf_dark_matter_cli-0.4.0.dist-info/top_level.txt
nsdf_dark_matter_cli-0.4.0.dist-info/RECORD
