Metadata-Version: 2.4
Name: nsdf-dark-matter-cli
Version: 0.4.0
Summary: NSDF Dark Matter CLI
Author-email: NSDF Team <info@nationalsciencedatafabric.org>
Project-URL: documentation, https://nsdf-fabric.github.io/nsdf-slac/
Project-URL: source, https://github.com/nsdf-fabric/nsdf-slac
Project-URL: tracker, https://github.com/nsdf-fabric/nsdf-slac/issues
Project-URL: release notes, https://github.com/nsdf-fabric/nsdf-slac/releases
Classifier: Intended Audience :: Science/Research
Classifier: Intended Audience :: Developers
Classifier: Programming Language :: Python
Classifier: Programming Language :: Python :: 3.10
Classifier: Topic :: Software Development
Classifier: Topic :: Scientific/Engineering
Requires-Python: >=3.10
Requires-Dist: typer==0.16.0
Requires-Dist: requests==2.32.4
